perkalian/__init__.py
perkalian/tabelperkalian.py
tabelperkalianiwan404-0.0.1.dist-info/LICENCE
tabelperkalianiwan404-0.0.1.dist-info/METADATA
tabelperkalianiwan404-0.0.1.dist-info/WHEEL
tabelperkalianiwan404-0.0.1.dist-info/top_level.txt
tabelperkalianiwan404-0.0.1.dist-info/RECORD
