Metadata-Version: 2.1
Name: tabelperkalianiwan404
Version: 0.0.1
Summary: Tabel perkalian simpel, yang membuat saya pusing menguploadnya ke pypi
Home-page: https://github.com/Zxnc0/TabelPerkalian
Author: Nur Ridwan
Author-email: nurridwan270305@gmail.com
Classifier: Programming Language :: Python :: 3
Classifier: License :: OSI Approved :: MIT License
Classifier: Operating System :: OS Independent
License-File: LICENCE
